__init__.py
formatting.py
spcjsonutils-0.1.2.dist-info/METADATA
spcjsonutils-0.1.2.dist-info/WHEEL
spcjsonutils-0.1.2.dist-info/top_level.txt
spcjsonutils-0.1.2.dist-info/RECORD
