Metadata-Version: 2.2
Name: spcjsonutils
Version: 0.1.2
Summary: JSON utility functions
Requires-Python: >=3.11
